README.rst
setup.py
pip_helloworld/__init__.py
pip_helloworld/foo.py
pip_helloworld.egg-info/PKG-INFO
pip_helloworld.egg-info/SOURCES.txt
pip_helloworld.egg-info/dependency_links.txt
pip_helloworld.egg-info/top_level.txt