Metadata-Version: 1.2
Name: pip-helloworld
Version: 0.0.12
Summary: A small example package
Home-page: https://github.com/pypa/sampleproject
Author: evoup
Author-email: evoex123@gmail.com
License: UNKNOWN
Platform: UNKNOWN
Classifier: Programming Language :: Python :: 3
Classifier: License :: OSI Approved :: MIT License
Classifier: Operating System :: OS Independent
Requires-Python: >=3.5
